<?xml version="1.0" encoding="UTF-8"?>
<inforef>
  <userref>
    <user>
      <id>10323</id>
    </user>
    <user>
      <id>10329</id>
    </user>
    <user>
      <id>3897</id>
    </user>
    <user>
      <id>10349</id>
    </user>
    <user>
      <id>10321</id>
    </user>
    <user>
      <id>10311</id>
    </user>
    <user>
      <id>1905</id>
    </user>
    <user>
      <id>10307</id>
    </user>
    <user>
      <id>10347</id>
    </user>
    <user>
      <id>3881</id>
    </user>
    <user>
      <id>10361</id>
    </user>
    <user>
      <id>3785</id>
    </user>
    <user>
      <id>10325</id>
    </user>
    <user>
      <id>3781</id>
    </user>
    <user>
      <id>10771</id>
    </user>
    <user>
      <id>10921</id>
    </user>
    <user>
      <id>10915</id>
    </user>
    <user>
      <id>10327</id>
    </user>
    <user>
      <id>3805</id>
    </user>
    <user>
      <id>3769</id>
    </user>
    <user>
      <id>2647</id>
    </user>
    <user>
      <id>3925</id>
    </user>
    <user>
      <id>10341</id>
    </user>
    <user>
      <id>3931</id>
    </user>
    <user>
      <id>3759</id>
    </user>
    <user>
      <id>3755</id>
    </user>
    <user>
      <id>3941</id>
    </user>
    <user>
      <id>3757</id>
    </user>
    <user>
      <id>10319</id>
    </user>
    <user>
      <id>3885</id>
    </user>
    <user>
      <id>3817</id>
    </user>
    <user>
      <id>10331</id>
    </user>
    <user>
      <id>3933</id>
    </user>
    <user>
      <id>10317</id>
    </user>
    <user>
      <id>3907</id>
    </user>
    <user>
      <id>3917</id>
    </user>
    <user>
      <id>3767</id>
    </user>
    <user>
      <id>10355</id>
    </user>
    <user>
      <id>10353</id>
    </user>
    <user>
      <id>10339</id>
    </user>
    <user>
      <id>11591</id>
    </user>
    <user>
      <id>10919</id>
    </user>
    <user>
      <id>6071</id>
    </user>
    <user>
      <id>10343</id>
    </user>
    <user>
      <id>10351</id>
    </user>
  </userref>
  <fileref>
    <file>
      <id>1169555</id>
    </file>
    <file>
      <id>1169557</id>
    </file>
    <file>
      <id>1169559</id>
    </file>
    <file>
      <id>1185455</id>
    </file>
    <file>
      <id>1185457</id>
    </file>
  </fileref>
</inforef>